LICENSE.txt
MANIFEST.in
README.md
setup.cfg
setup.py
data/data_file
oreaws/__init__.py
oreaws/awscli.py
oreaws.egg-info/PKG-INFO
oreaws.egg-info/SOURCES.txt
oreaws.egg-info/dependency_links.txt
oreaws.egg-info/entry_points.txt
oreaws.egg-info/requires.txt
oreaws.egg-info/top_level.txt
oreaws/modules/__init__.py
oreaws/modules/autoscaling.py
oreaws/modules/ec2.py
oreaws/modules/route53.py
oreaws/modules/s3.py