Metadata-Version: 1.0
Name: oreaws
Version: 0.0.48
Summary: Python AWS CLI Tool
Home-page: https://github.com/yhidetoshi/python-awscli-tool
Author: yhidetoshi
Author-email: example@python.net
License: MIT
Platform: any
